{
  "project_info": {
    "project_number": "1081867839828",
    "project_id": "social-media-app-1d429",
    "storage_bucket": "social-media-app-1d429.appspot.com"
  },
  "client": [
    {
      "client_info": {
        "mobilesdk_app_id": "1:1081867839828:android:37d551a46ed9dc173080c1",
        "android_client_info": {
          "package_name": "com.socialmediaapp"
        }
      },
      "oauth_client": [
        {
          "client_id": "1081867839828-hfo13qn7s6cvturs801cvfr2e4b396is.apps.googleusercontent.com",
          "client_type": 1,
          "android_info": {
            "package_name": "com.socialmediaapp",
            "certificate_hash": "1c1468fc3657230648b836d86dda2414910acec7"
          }
        },
        {
          "client_id": "1081867839828-0o6epdmk9t9duc1s95l65oged5ikc9cr.apps.googleusercontent.com",
          "client_type": 3
        }
      ],
      "api_key": [
        {
          "current_key": "AIzaSyCRKN0r774VcLy2WFSnyBaZF_Q8HFHTo6c"
        }
      ],
      "services": {
        "appinvite_service": {
          "other_platform_oauth_client": [
            {
              "client_id": "1081867839828-0o6epdmk9t9duc1s95l65oged5ikc9cr.apps.googleusercontent.com",
              "client_type": 3
            }
          ]
        }
      }
    }
  ],
  "configuration_version": "1"
}